odoo8_addon_document_page_environment_manual-8.0.1.0.0-py2.7-nspkg.pth
odoo_addons/document_page_environment_manual/__openerp__.py
odoo_addons/document_page_environment_manual/__init__.py
odoo_addons/document_page_environment_manual/migrations/7.0.1.0/pre-migration.py
odoo_addons/document_page_environment_manual/i18n/document_page_environment_manual.pot
odoo_addons/document_page_environment_manual/i18n/sl.po
odoo_addons/document_page_environment_manual/i18n/nb.po
odoo_addons/document_page_environment_manual/i18n/de.po
odoo_addons/document_page_environment_manual/i18n/vi.po
odoo_addons/document_page_environment_manual/i18n/fr.po
odoo_addons/document_page_environment_manual/i18n/pt_BR.po
odoo_addons/document_page_environment_manual/i18n/sv.po
odoo_addons/document_page_environment_manual/data/document_page.xml
odoo_addons/document_page_environment_manual/static/description/icon.png
odoo8_addon_document_page_environment_manual-8.0.1.0.0.dist-info/top_level.txt
odoo8_addon_document_page_environment_manual-8.0.1.0.0.dist-info/WHEEL
odoo8_addon_document_page_environment_manual-8.0.1.0.0.dist-info/RECORD
odoo8_addon_document_page_environment_manual-8.0.1.0.0.dist-info/metadata.json
odoo8_addon_document_page_environment_manual-8.0.1.0.0.dist-info/DESCRIPTION.rst
odoo8_addon_document_page_environment_manual-8.0.1.0.0.dist-info/METADATA
odoo8_addon_document_page_environment_manual-8.0.1.0.0.dist-info/namespace_packages.txt
